inte_screening/__init__.py
inte_screening/admin_site.py
inte_screening/apps.py
inte_screening/baker_recipes.py
inte_screening/choices.py
inte_screening/constants.py
inte_screening/eligibility.py
inte_screening/offline_models.py
inte_screening/urls.py
inte_screening/admin/__init__.py
inte_screening/admin/subject_refusal_admin.py
inte_screening/admin/subject_screening_admin.py
inte_screening/form_validators/__init__.py
inte_screening/form_validators/subject_refusal.py
inte_screening/form_validators/subject_screening.py
inte_screening/forms/__init__.py
inte_screening/forms/subject_refusal_form.py
inte_screening/forms/subject_screening_form.py
inte_screening/migrations/0001_initial.py
inte_screening/migrations/0002_auto_20200202_1111.py
inte_screening/migrations/0003_auto_20200202_2301.py
inte_screening/migrations/__init__.py
inte_screening/models/__init__.py
inte_screening/models/subject_refusal.py
inte_screening/models/subject_screening.py
inte_screening/tests/__init__.py
inte_screening/tests/inte_test_case_mixin.py
inte_screening/tests/options.py
inte_screening/tests/test_forms.py
screening_app/__init__.py
screening_app/admin.py
screening_app/apps.py
screening_app/models.py
screening_app/tests.py
screening_app/urls.py
screening_app/views.py
screening_app/migrations/__init__.py
inte_screening-0.1.5.dist-info/AUTHORS
inte_screening-0.1.5.dist-info/LICENSE
inte_screening-0.1.5.dist-info/METADATA
inte_screening-0.1.5.dist-info/WHEEL
inte_screening-0.1.5.dist-info/top_level.txt
inte_screening-0.1.5.dist-info/RECORD
